CHANGES.rst
MANIFEST.in
README.rst
setup.py
tomcom/__init__.py
tomcom.adapters.updateactualurl.egg-info/PKG-INFO
tomcom.adapters.updateactualurl.egg-info/SOURCES.txt
tomcom.adapters.updateactualurl.egg-info/dependency_links.txt
tomcom.adapters.updateactualurl.egg-info/entry_points.txt
tomcom.adapters.updateactualurl.egg-info/namespace_packages.txt
tomcom.adapters.updateactualurl.egg-info/not-zip-safe
tomcom.adapters.updateactualurl.egg-info/requires.txt
tomcom.adapters.updateactualurl.egg-info/top_level.txt
tomcom/adapters/__init__.py
tomcom/adapters/updateactualurl/__init__.py
tomcom/adapters/updateactualurl/adapter.py
tomcom/adapters/updateactualurl/configure.zcml