Metadata-Version: 1.1
Name: tomcom.adapters.updateactualurl
Version: 4.3.0.0
Summary: Little helpers
Home-page: https://github.com/tomcom-de/tomcom.adapters.updateactualurl
Author: tomcom GmbH
Author-email: mailto:info@tomcom.de
License: GPL2
Keywords: tomcom plone
Platform: UNKNOWN
Classifier: Framework :: Plone
Classifier: Framework :: Plone :: 4.3
Classifier: Programming Language :: Python
Classifier: Topic :: Software Development :: Libraries :: Python Modules
